Workbook
Name Plan: Dropdowns!$P$2:$P$7
Name Website_Platform: Dropdowns!$N$2:$N$13
Name Website_Quality: Dropdowns!$J$2:$J$7
Name Lost_Reason: Dropdowns!$M$2:$M$11
Name Contact_Method: Dropdowns!$C$2:$C$10
Name Contact_Role: Dropdowns!$R$2:$R$12
Name Business_Type: Dropdowns!$S$2:$S$8
Name Priority: Dropdowns!$G$2:$G$6
Name Decision_Maker: Dropdowns!$H$2:$H$4
Name Lead_Source: Dropdowns!$B$2:$B$12
Name Pain_Point: Dropdowns!$L$2:$L$16
Name Currency: Dropdowns!$Q$2:$Q$3
Name Yes_No: Dropdowns!$I$2:$I$4
Name Lead_Status: Dropdowns!$A$2:$A$12
Name Activity_Type: Dropdowns!$D$2:$D$12
Name Business_Size: Dropdowns!$K$2:$K$7
Name Activity_Outcome: Dropdowns!$E$2:$E$17
Name Source_Quality: Dropdowns!$T$2:$T$6
Name Customer_Status: Dropdowns!$U$2:$U$6
Name Research_Quality: Dropdowns!$V$2:$V$5
Name Pipeline_Stage: Dropdowns!$F$2:$F$11

Sheet Dashboard
A1: PEAK SALES INTELLIGENCE
A4: COMMAND CENTER | D4: SALES FUNNEL
A5: Total Leads | B5: =COUNTA(Leads!A2:A501) | D5: New | E5: =COUNTIF(Leads!AB2:AB501,"New")
A6: Active Prospects | B6: =COUNTIFS(Leads!AB2:AB501,"<>",Leads!AB2:AB501,"<>Customer",Leads!AB2:AB501,"<>Lost",Leads!AB2:AB501,"<>Disqualified") | D6: Contacted | E6: =COUNTIF(Leads!AB2:AB501,"Contacted")
A7: Contacted | B7: =COUNTIF(Leads!AB2:AB501,"Contacted") | D7: Engaged | E7: =COUNTIF(Leads!AB2:AB501,"Engaged")
A8: Qualified | B8: =COUNTIF(Leads!AB2:AB501,"Qualified") | D8: Qualified | E8: =COUNTIF(Leads!AB2:AB501,"Qualified")
A9: Demos Booked | B9: =COUNTIF(Leads!BO2:BO501,"Demo Booked") | D9: Demo | E9: =COUNTIF(Leads!BO2:BO501,"Demo Booked")+COUNTIF(Leads!BO2:BO501,"Demo Completed")
A10: Proposals | B10: =COUNTIF(Leads!BO2:BO501,"Proposal") | D10: Proposal | E10: =COUNTIF(Leads!BO2:BO501,"Proposal")
A11: Customers | B11: =COUNTIF(Leads!AB2:AB501,"Customer") | D11: Won | E11: =COUNTIF(Leads!AB2:AB501,"Customer")
A12: Pipeline MRR | B12: =SUM(Leads!BQ2:BQ501)
A15: 🔥 WHAT SHOULD I DO TODAY?
A16: Rank | B16: Business | C16: Industry | D16: Priority | E16: Temperature | F16: Score | G16: Follow-Up | H16: Reason | I16: Next Action
A17: =Call_Queue!A2 | B17: =Call_Queue!C2 | C17: =Call_Queue!C2 | D17: =Call_Queue!D2 | E17: =Call_Queue!E2 | F17: =Call_Queue!F2 | G17: =Call_Queue!G2 | H17: =Call_Queue!H2 | I17: =Call_Queue!I2
A18: =Call_Queue!A3 | B18: =Call_Queue!C3 | C18: =Call_Queue!C3 | D18: =Call_Queue!D3 | E18: =Call_Queue!E3 | F18: =Call_Queue!F3 | G18: =Call_Queue!G3 | H18: =Call_Queue!H3 | I18: =Call_Queue!I3
A19: =Call_Queue!A4 | B19: =Call_Queue!C4 | C19: =Call_Queue!C4 | D19: =Call_Queue!D4 | E19: =Call_Queue!E4 | F19: =Call_Queue!F4 | G19: =Call_Queue!G4 | H19: =Call_Queue!H4 | I19: =Call_Queue!I4
A20: =Call_Queue!A5 | B20: =Call_Queue!C5 | C20: =Call_Queue!C5 | D20: =Call_Queue!D5 | E20: =Call_Queue!E5 | F20: =Call_Queue!F5 | G20: =Call_Queue!G5 | H20: =Call_Queue!H5 | I20: =Call_Queue!I5
A21: =Call_Queue!A6 | B21: =Call_Queue!C6 | C21: =Call_Queue!C6 | D21: =Call_Queue!D6 | E21: =Call_Queue!E6 | F21: =Call_Queue!F6 | G21: =Call_Queue!G6 | H21: =Call_Queue!H6 | I21: =Call_Queue!I6
A22: =Call_Queue!A7 | B22: =Call_Queue!C7 | C22: =Call_Queue!C7 | D22: =Call_Queue!D7 | E22: =Call_Queue!E7 | F22: =Call_Queue!F7 | G22: =Call_Queue!G7 | H22: =Call_Queue!H7 | I22: =Call_Queue!I7
A23: =Call_Queue!A8 | B23: =Call_Queue!C8 | C23: =Call_Queue!C8 | D23: =Call_Queue!D8 | E23: =Call_Queue!E8 | F23: =Call_Queue!F8 | G23: =Call_Queue!G8 | H23: =Call_Queue!H8 | I23: =Call_Queue!I8
A24: =Call_Queue!A9 | B24: =Call_Queue!C9 | C24: =Call_Queue!C9 | D24: =Call_Queue!D9 | E24: =Call_Queue!E9 | F24: =Call_Queue!F9 | G24: =Call_Queue!G9 | H24: =Call_Queue!H9 | I24: =Call_Queue!I9
A25: =Call_Queue!A10 | B25: =Call_Queue!C10 | C25: =Call_Queue!C10 | D25: =Call_Queue!D10 | E25: =Call_Queue!E10 | F25: =Call_Queue!F10 | G25: =Call_Queue!G10 | H25: =Call_Queue!H10 | I25: =Call_Queue!I10
A26: =Call_Queue!A11 | B26: =Call_Queue!C11 | C26: =Call_Queue!C11 | D26: =Call_Queue!D11 | E26: =Call_Queue!E11 | F26: =Call_Queue!F11 | G26: =Call_Queue!G11 | H26: =Call_Queue!H11 | I26: =Call_Queue!I11

Sheet Call_Queue
A1: Rank | B1: Lead ID | C1: Business Name | D1: Industry | E1: City | F1: Priority | G1: Temperature | H1: Score | I1: Next Follow-Up | J1: Last Contact | K1: Attempts | L1: Primary Pain Point | M1: Plan | N1: Reason To Call | O1: Next Action
A2: =IF(B2="","",RANK(H2,$H$2:$H$51,0)) | B2: {=IFERROR(INDEX(Leads!$A:$A,MATCH(LARGE(Leads!$BL$2:$BL$501,ROW()-1),Leads!$BL:$BL,0)),"")} | C2: {=IFERROR(INDEX(Leads!$B:$B,MATCH(B2,Leads!$A:$A,0)),"")} | D2: {=IFERROR(INDEX(Leads!$E:$E,MATCH(B2,Leads!$A:$A,0)),"")} | E2: {=IFERROR(INDEX(Leads!$K:$K,MATCH(B2,Leads!$A:$A,0)),"")} | F2: {=IFERROR(INDEX(Leads!$AC:$AC,MATCH(B2,Leads!$A:$A,0)),"")} | G2: {=IFERROR(INDEX(Leads!$BM:$BM,MATCH(B2,Leads!$A:$A,0)),"")} | H2: {=IFERROR(INDEX(Leads!$BL:$BL,MATCH(B2,Leads!$A:$A,0)),"")} | I2: {=IFERROR(INDEX(Leads!$AF:$AF,MATCH(B2,Leads!$A:$A,0)),"")} | J2: {=IFERROR(INDEX(Leads!$AE:$AE,MATCH(B2,Leads!$A:$A,0)),"")} | K2: {=IFERROR(INDEX(Leads!$AG:$AG,MATCH(B2,Leads!$A:$A,0)),"")} | L2: {=IFERROR(INDEX(Leads!$AZ:$AZ,MATCH(B2,Leads!$A:$A,0)),"")} | M2: {=IFERROR(INDEX(Leads!$BB:$BB,MATCH(B2,Leads!$A:$A,0)),"")} | N2: =IF(I2="","",IF(I2=TODAY(),"FOLLOW UP TODAY",IF(I2<TODAY(),"OVERDUE","HIGH SCORE"))) | O2: =IF(N2="FOLLOW UP TODAY","Call / follow up",IF(N2="OVERDUE","Call now","Prioritize outreach"))
A3: =IF(B3="","",RANK(H3,$H$2:$H$51,0)) | B3: {=IFERROR(INDEX(Leads!$A:$A,MATCH(LARGE(Leads!$BL$2:$BL$501,ROW()-1),Leads!$BL:$BL,0)),"")} | C3: {=IFERROR(INDEX(Leads!$B:$B,MATCH(B3,Leads!$A:$A,0)),"")} | D3: {=IFERROR(INDEX(Leads!$E:$E,MATCH(B3,Leads!$A:$A,0)),"")} | E3: {=IFERROR(INDEX(Leads!$K:$K,MATCH(B3,Leads!$A:$A,0)),"")} | F3: {=IFERROR(INDEX(Leads!$AC:$AC,MATCH(B3,Leads!$A:$A,0)),"")} | G3: {=IFERROR(INDEX(Leads!$BM:$BM,MATCH(B3,Leads!$A:$A,0)),"")} | H3: {=IFERROR(INDEX(Leads!$BL:$BL,MATCH(B3,Leads!$A:$A,0)),"")} | I3: {=IFERROR(INDEX(Leads!$AF:$AF,MATCH(B3,Leads!$A:$A,0)),"")} | J3: {=IFERROR(INDEX(Leads!$AE:$AE,MATCH(B3,Leads!$A:$A,0)),"")} | K3: {=IFERROR(INDEX(Leads!$AG:$AG,MATCH(B3,Leads!$A:$A,0)),"")} | L3: {=IFERROR(INDEX(Leads!$AZ:$AZ,MATCH(B3,Leads!$A:$A,0)),"")} | M3: {=IFERROR(INDEX(Leads!$BB:$BB,MATCH(B3,Leads!$A:$A,0)),"")} | N3: =IF(I3="","",IF(I3=TODAY(),"FOLLOW UP TODAY",IF(I3<TODAY(),"OVERDUE","HIGH SCORE"))) | O3: =IF(N3="FOLLOW UP TODAY","Call / follow up",IF(N3="OVERDUE","Call now","Prioritize outreach"))
A4: =IF(B4="","",RANK(H4,$H$2:$H$51,0)) | B4: {=IFERROR(INDEX(Leads!$A:$A,MATCH(LARGE(Leads!$BL$2:$BL$501,ROW()-1),Leads!$BL:$BL,0)),"")} | C4: {=IFERROR(INDEX(Leads!$B:$B,MATCH(B4,Leads!$A:$A,0)),"")} | D4: {=IFERROR(INDEX(Leads!$E:$E,MATCH(B4,Leads!$A:$A,0)),"")} | E4: {=IFERROR(INDEX(Leads!$K:$K,MATCH(B4,Leads!$A:$A,0)),"")} | F4: {=IFERROR(INDEX(Leads!$AC:$AC,MATCH(B4,Leads!$A:$A,0)),"")} | G4: {=IFERROR(INDEX(Leads!$BM:$BM,MATCH(B4,Leads!$A:$A,0)),"")} | H4: {=IFERROR(INDEX(Leads!$BL:$BL,MATCH(B4,Leads!$A:$A,0)),"")} | I4: {=IFERROR(INDEX(Leads!$AF:$AF,MATCH(B4,Leads!$A:$A,0)),"")} | J4: {=IFERROR(INDEX(Leads!$AE:$AE,MATCH(B4,Leads!$A:$A,0)),"")} | K4: {=IFERROR(INDEX(Leads!$AG:$AG,MATCH(B4,Leads!$A:$A,0)),"")} | L4: {=IFERROR(INDEX(Leads!$AZ:$AZ,MATCH(B4,Leads!$A:$A,0)),"")} | M4: {=IFERROR(INDEX(Leads!$BB:$BB,MATCH(B4,Leads!$A:$A,0)),"")} | N4: =IF(I4="","",IF(I4=TODAY(),"FOLLOW UP TODAY",IF(I4<TODAY(),"OVERDUE","HIGH SCORE"))) | O4: =IF(N4="FOLLOW UP TODAY","Call / follow up",IF(N4="OVERDUE","Call now","Prioritize outreach"))
A5: =IF(B5="","",RANK(H5,$H$2:$H$51,0)) | B5: {=IFERROR(INDEX(Leads!$A:$A,MATCH(LARGE(Leads!$BL$2:$BL$501,ROW()-1),Leads!$BL:$BL,0)),"")} | C5: {=IFERROR(INDEX(Leads!$B:$B,MATCH(B5,Leads!$A:$A,0)),"")} | D5: {=IFERROR(INDEX(Leads!$E:$E,MATCH(B5,Leads!$A:$A,0)),"")} | E5: {=IFERROR(INDEX(Leads!$K:$K,MATCH(B5,Leads!$A:$A,0)),"")} | F5: {=IFERROR(INDEX(Leads!$AC:$AC,MATCH(B5,Leads!$A:$A,0)),"")} | G5: {=IFERROR(INDEX(Leads!$BM:$BM,MATCH(B5,Leads!$A:$A,0)),"")} | H5: {=IFERROR(INDEX(Leads!$BL:$BL,MATCH(B5,Leads!$A:$A,0)),"")} | I5: {=IFERROR(INDEX(Leads!$AF:$AF,MATCH(B5,Leads!$A:$A,0)),"")} | J5: {=IFERROR(INDEX(Leads!$AE:$AE,MATCH(B5,Leads!$A:$A,0)),"")} | K5: {=IFERROR(INDEX(Leads!$AG:$AG,MATCH(B5,Leads!$A:$A,0)),"")} | L5: {=IFERROR(INDEX(Leads!$AZ:$AZ,MATCH(B5,Leads!$A:$A,0)),"")} | M5: {=IFERROR(INDEX(Leads!$BB:$BB,MATCH(B5,Leads!$A:$A,0)),"")} | N5: =IF(I5="","",IF(I5=TODAY(),"FOLLOW UP TODAY",IF(I5<TODAY(),"OVERDUE","HIGH SCORE"))) | O5: =IF(N5="FOLLOW UP TODAY","Call / follow up",IF(N5="OVERDUE","Call now","Prioritize outreach"))
A6: =IF(B6="","",RANK(H6,$H$2:$H$51,0)) | B6: {=IFERROR(INDEX(Leads!$A:$A,MATCH(LARGE(Leads!$BL$2:$BL$501,ROW()-1),Leads!$BL:$BL,0)),"")} | C6: {=IFERROR(INDEX(Leads!$B:$B,MATCH(B6,Leads!$A:$A,0)),"")} | D6: {=IFERROR(INDEX(Leads!$E:$E,MATCH(B6,Leads!$A:$A,0)),"")} | E6: {=IFERROR(INDEX(Leads!$K:$K,MATCH(B6,Leads!$A:$A,0)),"")} | F6: {=IFERROR(INDEX(Leads!$AC:$AC,MATCH(B6,Leads!$A:$A,0)),"")} | G6: {=IFERROR(INDEX(Leads!$BM:$BM,MATCH(B6,Leads!$A:$A,0)),"")} | H6: {=IFERROR(INDEX(Leads!$BL:$BL,MATCH(B6,Leads!$A:$A,0)),"")} | I6: {=IFERROR(INDEX(Leads!$AF:$AF,MATCH(B6,Leads!$A:$A,0)),"")} | J6: {=IFERROR(INDEX(Leads!$AE:$AE,MATCH(B6,Leads!$A:$A,0)),"")} | K6: {=IFERROR(INDEX(Leads!$AG:$AG,MATCH(B6,Leads!$A:$A,0)),"")} | L6: {=IFERROR(INDEX(Leads!$AZ:$AZ,MATCH(B6,Leads!$A:$A,0)),"")} | M6: {=IFERROR(INDEX(Leads!$BB:$BB,MATCH(B6,Leads!$A:$A,0)),"")} | N6: =IF(I6="","",IF(I6=TODAY(),"FOLLOW UP TODAY",IF(I6<TODAY(),"OVERDUE","HIGH SCORE"))) | O6: =IF(N6="FOLLOW UP TODAY","Call / follow up",IF(N6="OVERDUE","Call now","Prioritize outreach"))
A7: =IF(B7="","",RANK(H7,$H$2:$H$51,0)) | B7: {=IFERROR(INDEX(Leads!$A:$A,MATCH(LARGE(Leads!$BL$2:$BL$501,ROW()-1),Leads!$BL:$BL,0)),"")} | C7: {=IFERROR(INDEX(Leads!$B:$B,MATCH(B7,Leads!$A:$A,0)),"")} | D7: {=IFERROR(INDEX(Leads!$E:$E,MATCH(B7,Leads!$A:$A,0)),"")} | E7: {=IFERROR(INDEX(Leads!$K:$K,MATCH(B7,Leads!$A:$A,0)),"")} | F7: {=IFERROR(INDEX(Leads!$AC:$AC,MATCH(B7,Leads!$A:$A,0)),"")} | G7: {=IFERROR(INDEX(Leads!$BM:$BM,MATCH(B7,Leads!$A:$A,0)),"")} | H7: {=IFERROR(INDEX(Leads!$BL:$BL,MATCH(B7,Leads!$A:$A,0)),"")} | I7: {=IFERROR(INDEX(Leads!$AF:$AF,MATCH(B7,Leads!$A:$A,0)),"")} | J7: {=IFERROR(INDEX(Leads!$AE:$AE,MATCH(B7,Leads!$A:$A,0)),"")} | K7: {=IFERROR(INDEX(Leads!$AG:$AG,MATCH(B7,Leads!$A:$A,0)),"")} | L7: {=IFERROR(INDEX(Leads!$AZ:$AZ,MATCH(B7,Leads!$A:$A,0)),"")} | M7: {=IFERROR(INDEX(Leads!$BB:$BB,MATCH(B7,Leads!$A:$A,0)),"")} | N7: =IF(I7="","",IF(I7=TODAY(),"FOLLOW UP TODAY",IF(I7<TODAY(),"OVERDUE","HIGH SCORE"))) | O7: =IF(N7="FOLLOW UP TODAY","Call / follow up",IF(N7="OVERDUE","Call now","Prioritize outreach"))
A8: =IF(B8="","",RANK(H8,$H$2:$H$51,0)) | B8: {=IFERROR(INDEX(Leads!$A:$A,MATCH(LARGE(Leads!$BL$2:$BL$501,ROW()-1),Leads!$BL:$BL,0)),"")} | C8: {=IFERROR(INDEX(Leads!$B:$B,MATCH(B8,Leads!$A:$A,0)),"")} | D8: {=IFERROR(INDEX(Leads!$E:$E,MATCH(B8,Leads!$A:$A,0)),"")} | E8: {=IFERROR(INDEX(Leads!$K:$K,MATCH(B8,Leads!$A:$A,0)),"")} | F8: {=IFERROR(INDEX(Leads!$AC:$AC,MATCH(B8,Leads!$A:$A,0)),"")} | G8: {=IFERROR(INDEX(Leads!$BM:$BM,MATCH(B8,Leads!$A:$A,0)),"")} | H8: {=IFERROR(INDEX(Leads!$BL:$BL,MATCH(B8,Leads!$A:$A,0)),"")} | I8: {=IFERROR(INDEX(Leads!$AF:$AF,MATCH(B8,Leads!$A:$A,0)),"")} | J8: {=IFERROR(INDEX(Leads!$AE:$AE,MATCH(B8,Leads!$A:$A,0)),"")} | K8: {=IFERROR(INDEX(Leads!$AG:$AG,MATCH(B8,Leads!$A:$A,0)),"")} | L8: {=IFERROR(INDEX(Leads!$AZ:$AZ,MATCH(B8,Leads!$A:$A,0)),"")} | M8: {=IFERROR(INDEX(Leads!$BB:$BB,MATCH(B8,Leads!$A:$A,0)),"")} | N8: =IF(I8="","",IF(I8=TODAY(),"FOLLOW UP TODAY",IF(I8<TODAY(),"OVERDUE","HIGH SCORE"))) | O8: =IF(N8="FOLLOW UP TODAY","Call / follow up",IF(N8="OVERDUE","Call now","Prioritize outreach"))
A9: =IF(B9="","",RANK(H9,$H$2:$H$51,0)) | B9: {=IFERROR(INDEX(Leads!$A:$A,MATCH(LARGE(Leads!$BL$2:$BL$501,ROW()-1),Leads!$BL:$BL,0)),"")} | C9: {=IFERROR(INDEX(Leads!$B:$B,MATCH(B9,Leads!$A:$A,0)),"")} | D9: {=IFERROR(INDEX(Leads!$E:$E,MATCH(B9,Leads!$A:$A,0)),"")} | E9: {=IFERROR(INDEX(Leads!$K:$K,MATCH(B9,Leads!$A:$A,0)),"")} | F9: {=IFERROR(INDEX(Leads!$AC:$AC,MATCH(B9,Leads!$A:$A,0)),"")} | G9: {=IFERROR(INDEX(Leads!$BM:$BM,MATCH(B9,Leads!$A:$A,0)),"")} | H9: {=IFERROR(INDEX(Leads!$BL:$BL,MATCH(B9,Leads!$A:$A,0)),"")} | I9: {=IFERROR(INDEX(Leads!$AF:$AF,MATCH(B9,Leads!$A:$A,0)),"")} | J9: {=IFERROR(INDEX(Leads!$AE:$AE,MATCH(B9,Leads!$A:$A,0)),"")} | K9: {=IFERROR(INDEX(Leads!$AG:$AG,MATCH(B9,Leads!$A:$A,0)),"")} | L9: {=IFERROR(INDEX(Leads!$AZ:$AZ,MATCH(B9,Leads!$A:$A,0)),"")} | M9: {=IFERROR(INDEX(Leads!$BB:$BB,MATCH(B9,Leads!$A:$A,0)),"")} | N9: =IF(I9="","",IF(I9=TODAY(),"FOLLOW UP TODAY",IF(I9<TODAY(),"OVERDUE","HIGH SCORE"))) | O9: =IF(N9="FOLLOW UP TODAY","Call / follow up",IF(N9="OVERDUE","Call now","Prioritize outreach"))
A10: =IF(B10="","",RANK(H10,$H$2:$H$51,0)) | B10: {=IFERROR(INDEX(Leads!$A:$A,MATCH(LARGE(Leads!$BL$2:$BL$501,ROW()-1),Leads!$BL:$BL,0)),"")} | C10: {=IFERROR(INDEX(Leads!$B:$B,MATCH(B10,Leads!$A:$A,0)),"")} | D10: {=IFERROR(INDEX(Leads!$E:$E,MATCH(B10,Leads!$A:$A,0)),"")} | E10: {=IFERROR(INDEX(Leads!$K:$K,MATCH(B10,Leads!$A:$A,0)),"")} | F10: {=IFERROR(INDEX(Leads!$AC:$AC,MATCH(B10,Leads!$A:$A,0)),"")} | G10: {=IFERROR(INDEX(Leads!$BM:$BM,MATCH(B10,Leads!$A:$A,0)),"")} | H10: {=IFERROR(INDEX(Leads!$BL:$BL,MATCH(B10,Leads!$A:$A,0)),"")} | I10: {=IFERROR(INDEX(Leads!$AF:$AF,MATCH(B10,Leads!$A:$A,0)),"")} | J10: {=IFERROR(INDEX(Leads!$AE:$AE,MATCH(B10,Leads!$A:$A,0)),"")} | K10: {=IFERROR(INDEX(Leads!$AG:$AG,MATCH(B10,Leads!$A:$A,0)),"")} | L10: {=IFERROR(INDEX(Leads!$AZ:$AZ,MATCH(B10,Leads!$A:$A,0)),"")} | M10: {=IFERROR(INDEX(Leads!$BB:$BB,MATCH(B10,Leads!$A:$A,0)),"")} | N10: =IF(I10="","",IF(I10=TODAY(),"FOLLOW UP TODAY",IF(I10<TODAY(),"OVERDUE","HIGH SCORE"))) | O10: =IF(N10="FOLLOW UP TODAY","Call / follow up",IF(N10="OVERDUE","Call now","Prioritize outreach"))
A11: =IF(B11="","",RANK(H11,$H$2:$H$51,0)) | B11: {=IFERROR(INDEX(Leads!$A:$A,MATCH(LARGE(Leads!$BL$2:$BL$501,ROW()-1),Leads!$BL:$BL,0)),"")} | C11: {=IFERROR(INDEX(Leads!$B:$B,MATCH(B11,Leads!$A:$A,0)),"")} | D11: {=IFERROR(INDEX(Leads!$E:$E,MATCH(B11,Leads!$A:$A,0)),"")} | E11: {=IFERROR(INDEX(Leads!$K:$K,MATCH(B11,Leads!$A:$A,0)),"")} | F11: {=IFERROR(INDEX(Leads!$AC:$AC,MATCH(B11,Leads!$A:$A,0)),"")} | G11: {=IFERROR(INDEX(Leads!$BM:$BM,MATCH(B11,Leads!$A:$A,0)),"")} | H11: {=IFERROR(INDEX(Leads!$BL:$BL,MATCH(B11,Leads!$A:$A,0)),"")} | I11: {=IFERROR(INDEX(Leads!$AF:$AF,MATCH(B11,Leads!$A:$A,0)),"")} | J11: {=IFERROR(INDEX(Leads!$AE:$AE,MATCH(B11,Leads!$A:$A,0)),"")} | K11: {=IFERROR(INDEX(Leads!$AG:$AG,MATCH(B11,Leads!$A:$A,0)),"")} | L11: {=IFERROR(INDEX(Leads!$AZ:$AZ,MATCH(B11,Leads!$A:$A,0)),"")} | M11: {=IFERROR(INDEX(Leads!$BB:$BB,MATCH(B11,Leads!$A:$A,0)),"")} | N11: =IF(I11="","",IF(I11=TODAY(),"FOLLOW UP TODAY",IF(I11<TODAY(),"OVERDUE","HIGH SCORE"))) | O11: =IF(N11="FOLLOW UP TODAY","Call / follow up",IF(N11="OVERDUE","Call now","Prioritize outreach"))
A12: =IF(B12="","",RANK(H12,$H$2:$H$51,0)) | B12: {=IFERROR(INDEX(Leads!$A:$A,MATCH(LARGE(Leads!$BL$2:$BL$501,ROW()-1),Leads!$BL:$BL,0)),"")} | C12: {=IFERROR(INDEX(Leads!$B:$B,MATCH(B12,Leads!$A:$A,0)),"")} | D12: {=IFERROR(INDEX(Leads!$E:$E,MATCH(B12,Leads!$A:$A,0)),"")} | E12: {=IFERROR(INDEX(Leads!$K:$K,MATCH(B12,Leads!$A:$A,0)),"")} | F12: {=IFERROR(INDEX(Leads!$AC:$AC,MATCH(B12,Leads!$A:$A,0)),"")} | G12: {=IFERROR(INDEX(Leads!$BM:$BM,MATCH(B12,Leads!$A:$A,0)),"")} | H12: {=IFERROR(INDEX(Leads!$BL:$BL,MATCH(B12,Leads!$A:$A,0)),"")} | I12: {=IFERROR(INDEX(Leads!$AF:$AF,MATCH(B12,Leads!$A:$A,0)),"")} | J12: {=IFERROR(INDEX(Leads!$AE:$AE,MATCH(B12,Leads!$A:$A,0)),"")} | K12: {=IFERROR(INDEX(Leads!$AG:$AG,MATCH(B12,Leads!$A:$A,0)),"")} | L12: {=IFERROR(INDEX(Leads!$AZ:$AZ,MATCH(B12,Leads!$A:$A,0)),"")} | M12: {=IFERROR(INDEX(Leads!$BB:$BB,MATCH(B12,Leads!$A:$A,0)),"")} | N12: =IF(I12="","",IF(I12=TODAY(),"FOLLOW UP TODAY",IF(I12<TODAY(),"OVERDUE","HIGH SCORE"))) | O12: =IF(N12="FOLLOW UP TODAY","Call / follow up",IF(N12="OVERDUE","Call now","Prioritize outreach"))
A13: =IF(B13="","",RANK(H13,$H$2:$H$51,0)) | B13: {=IFERROR(INDEX(Leads!$A:$A,MATCH(LARGE(Leads!$BL$2:$BL$501,ROW()-1),Leads!$BL:$BL,0)),"")} | C13: {=IFERROR(INDEX(Leads!$B:$B,MATCH(B13,Leads!$A:$A,0)),"")} | D13: {=IFERROR(INDEX(Leads!$E:$E,MATCH(B13,Leads!$A:$A,0)),"")} | E13: {=IFERROR(INDEX(Leads!$K:$K,MATCH(B13,Leads!$A:$A,0)),"")} | F13: {=IFERROR(INDEX(Leads!$AC:$AC,MATCH(B13,Leads!$A:$A,0)),"")} | G13: {=IFERROR(INDEX(Leads!$BM:$BM,MATCH(B13,Leads!$A:$A,0)),"")} | H13: {=IFERROR(INDEX(Leads!$BL:$BL,MATCH(B13,Leads!$A:$A,0)),"")} | I13: {=IFERROR(INDEX(Leads!$AF:$AF,MATCH(B13,Leads!$A:$A,0)),"")} | J13: {=IFERROR(INDEX(Leads!$AE:$AE,MATCH(B13,Leads!$A:$A,0)),"")} | K13: {=IFERROR(INDEX(Leads!$AG:$AG,MATCH(B13,Leads!$A:$A,0)),"")} | L13: {=IFERROR(INDEX(Leads!$AZ:$AZ,MATCH(B13,Leads!$A:$A,0)),"")} | M13: {=IFERROR(INDEX(Leads!$BB:$BB,MATCH(B13,Leads!$A:$A,0)),"")} | N13: =IF(I13="","",IF(I13=TODAY(),"FOLLOW UP TODAY",IF(I13<TODAY(),"OVERDUE","HIGH SCORE"))) | O13: =IF(N13="FOLLOW UP TODAY","Call / follow up",IF(N13="OVERDUE","Call now","Prioritize outreach"))
... A51: =IF(B51="","",RANK(H51,$H$2:$H$51,0)) | B51: {=IFERROR(INDEX(Leads!$A:$A,MATCH(LARGE(Leads!$BL$2:$BL$501,ROW()-1),Leads!$BL:$BL,0)),"")} | C51: {=IFERROR(INDEX(Leads!$B:$B,MATCH(B51,Leads!$A:$A,0)),"")} | D51: {=IFERROR(INDEX(Leads!$E:$E,MATCH(B51,Leads!$A:$A,0)),"")} | E51: {=IFERROR(INDEX(Leads!$K:$K,MATCH(B51,Leads!$A:$A,0)),"")} | F51: {=IFERROR(INDEX(Leads!$AC:$AC,MATCH(B51,Leads!$A:$A,0)),"")} | G51: {=IFERROR(INDEX(Leads!$BM:$BM,MATCH(B51,Leads!$A:$A,0)),"")} | H51: {=IFERROR(INDEX(Leads!$BL:$BL,MATCH(B51,Leads!$A:$A,0)),"")} | I51: {=IFERROR(INDEX(Leads!$AF:$AF,MATCH(B51,Leads!$A:$A,0)),"")} | J51: {=IFERROR(INDEX(Leads!$AE:$AE,MATCH(B51,Leads!$A:$A,0)),"")} | K51: {=IFERROR(INDEX(Leads!$AG:$AG,MATCH(B51,Leads!$A:$A,0)),"")} | L51: {=IFERROR(INDEX(Leads!$AZ:$AZ,MATCH(B51,Leads!$A:$A,0)),"")} | M51: {=IFERROR(INDEX(Leads!$BB:$BB,MATCH(B51,Leads!$A:$A,0)),"")} | N51: =IF(I51="","",IF(I51=TODAY(),"FOLLOW UP TODAY",IF(I51<TODAY(),"OVERDUE","HIGH SCORE"))) | O51: =IF(N51="FOLLOW UP TODAY","Call / follow up",IF(N51="OVERDUE","Call now","Prioritize outreach"))

Sheet Leads
A1: Lead ID | B1: Business Name | C1: Legal / DBA Name | D1: Business Type | E1: Industry | F1: Sub-Industry | G1: Service Type | H1: Website | I1: Phone | J1: Email | K1: City | L1: Province/State | M1: Country | N1: Postal/ZIP | O1: Service Area | P1: Locations | Q1: Primary Contact | R1: Contact Role | S1: Decision Maker? | T1: Contact Phone | U1: Contact Email | V1: LinkedIn | W1: Instagram | X1: Facebook | Y1: Lead Source | Z1: Source Detail | AA1: Source Quality | AB1: Lead Status | AC1: Priority | AD1: Date Added | AE1: Last Contact | AF1: Next Follow-Up | AG1: Contact Attempts | AH1: Last Outcome | AI1: Business Size | AJ1: Employees | AK1: Estimated Revenue | AL1: Years in Business | AM1: Google Rating | AN1: Review Count | AO1: Social Followers | AP1: Website Platform | AQ1: Website Quality | AR1: Current Booking | AS1: Current Payments | AT1: Current CRM | AU1: Current Accounting | AV1: Current Invoicing | AW1: Current Email Marketing | AX1: Current POS | AY1: Pain Points | AZ1: Primary Pain Point | BA1: Peak Opportunity | BB1: Recommended Plan | BC1: Fit Score | BD1: Engagement Score | BE1: Buying Potential Score | BF1: Accessibility Score | BG1: Total Lead Score | BH1: Lead Temperature | BI1: Pipeline Stage | BJ1: Opportunity ID | BK1: Estimated Deal Value | BL1: Estimated MRR | BM1: Expected Close | BN1: Lost Reason | BO1: Notes
AE2: =IF(A2="","",IFERROR(MAXIFS(Activities!$D:$D,Activities!$B:$B,A2),"")) | AF2: =IF(A2="","",IFERROR(MINIFS(Follow_Ups!$G:$G,Follow_Ups!$B:$B,A2,Follow_Ups!$H:$H,"<>Completed",Follow_Ups!$G:$G,">="&TODAY()),"")) | AG2: =IF(A2="","",COUNTIF(Activities!$B:$B,A2)) | BG2: =IF(COUNTA(BH2:BK2)=0,"",ROUND(AVERAGE(BH2:BK2),0)) | BH2: =IF(BL2="","",IF(BL2>=90,"HOT",IF(BL2>=75,"HIGH",IF(BL2>=50,"MEDIUM","LOW")))) | BL2: =IFERROR(BN2/12,"")
AE3: =IF(A3="","",IFERROR(MAXIFS(Activities!$D:$D,Activities!$B:$B,A3),"")) | AF3: =IF(A3="","",IFERROR(MINIFS(Follow_Ups!$G:$G,Follow_Ups!$B:$B,A3,Follow_Ups!$H:$H,"<>Completed",Follow_Ups!$G:$G,">="&TODAY()),"")) | AG3: =IF(A3="","",COUNTIF(Activities!$B:$B,A3)) | BG3: =IF(COUNTA(BH3:BK3)=0,"",ROUND(AVERAGE(BH3:BK3),0)) | BH3: =IF(BL3="","",IF(BL3>=90,"HOT",IF(BL3>=75,"HIGH",IF(BL3>=50,"MEDIUM","LOW")))) | BL3: =IFERROR(BN3/12,"")
AE4: =IF(A4="","",IFERROR(MAXIFS(Activities!$D:$D,Activities!$B:$B,A4),"")) | AF4: =IF(A4="","",IFERROR(MINIFS(Follow_Ups!$G:$G,Follow_Ups!$B:$B,A4,Follow_Ups!$H:$H,"<>Completed",Follow_Ups!$G:$G,">="&TODAY()),"")) | AG4: =IF(A4="","",COUNTIF(Activities!$B:$B,A4)) | BG4: =IF(COUNTA(BH4:BK4)=0,"",ROUND(AVERAGE(BH4:BK4),0)) | BH4: =IF(BL4="","",IF(BL4>=90,"HOT",IF(BL4>=75,"HIGH",IF(BL4>=50,"MEDIUM","LOW")))) | BL4: =IFERROR(BN4/12,"")
AE5: =IF(A5="","",IFERROR(MAXIFS(Activities!$D:$D,Activities!$B:$B,A5),"")) | AF5: =IF(A5="","",IFERROR(MINIFS(Follow_Ups!$G:$G,Follow_Ups!$B:$B,A5,Follow_Ups!$H:$H,"<>Completed",Follow_Ups!$G:$G,">="&TODAY()),"")) | AG5: =IF(A5="","",COUNTIF(Activities!$B:$B,A5)) | BG5: =IF(COUNTA(BH5:BK5)=0,"",ROUND(AVERAGE(BH5:BK5),0)) | BH5: =IF(BL5="","",IF(BL5>=90,"HOT",IF(BL5>=75,"HIGH",IF(BL5>=50,"MEDIUM","LOW")))) | BL5: =IFERROR(BN5/12,"")
AE6: =IF(A6="","",IFERROR(MAXIFS(Activities!$D:$D,Activities!$B:$B,A6),"")) | AF6: =IF(A6="","",IFERROR(MINIFS(Follow_Ups!$G:$G,Follow_Ups!$B:$B,A6,Follow_Ups!$H:$H,"<>Completed",Follow_Ups!$G:$G,">="&TODAY()),"")) | AG6: =IF(A6="","",COUNTIF(Activities!$B:$B,A6)) | BG6: =IF(COUNTA(BH6:BK6)=0,"",ROUND(AVERAGE(BH6:BK6),0)) | BH6: =IF(BL6="","",IF(BL6>=90,"HOT",IF(BL6>=75,"HIGH",IF(BL6>=50,"MEDIUM","LOW")))) | BL6: =IFERROR(BN6/12,"")
AE7: =IF(A7="","",IFERROR(MAXIFS(Activities!$D:$D,Activities!$B:$B,A7),"")) | AF7: =IF(A7="","",IFERROR(MINIFS(Follow_Ups!$G:$G,Follow_Ups!$B:$B,A7,Follow_Ups!$H:$H,"<>Completed",Follow_Ups!$G:$G,">="&TODAY()),"")) | AG7: =IF(A7="","",COUNTIF(Activities!$B:$B,A7)) | BG7: =IF(COUNTA(BH7:BK7)=0,"",ROUND(AVERAGE(BH7:BK7),0)) | BH7: =IF(BL7="","",IF(BL7>=90,"HOT",IF(BL7>=75,"HIGH",IF(BL7>=50,"MEDIUM","LOW")))) | BL7: =IFERROR(BN7/12,"")
AE8: =IF(A8="","",IFERROR(MAXIFS(Activities!$D:$D,Activities!$B:$B,A8),"")) | AF8: =IF(A8="","",IFERROR(MINIFS(Follow_Ups!$G:$G,Follow_Ups!$B:$B,A8,Follow_Ups!$H:$H,"<>Completed",Follow_Ups!$G:$G,">="&TODAY()),"")) | AG8: =IF(A8="","",COUNTIF(Activities!$B:$B,A8)) | BG8: =IF(COUNTA(BH8:BK8)=0,"",ROUND(AVERAGE(BH8:BK8),0)) | BH8: =IF(BL8="","",IF(BL8>=90,"HOT",IF(BL8>=75,"HIGH",IF(BL8>=50,"MEDIUM","LOW")))) | BL8: =IFERROR(BN8/12,"")
AE9: =IF(A9="","",IFERROR(MAXIFS(Activities!$D:$D,Activities!$B:$B,A9),"")) | AF9: =IF(A9="","",IFERROR(MINIFS(Follow_Ups!$G:$G,Follow_Ups!$B:$B,A9,Follow_Ups!$H:$H,"<>Completed",Follow_Ups!$G:$G,">="&TODAY()),"")) | AG9: =IF(A9="","",COUNTIF(Activities!$B:$B,A9)) | BG9: =IF(COUNTA(BH9:BK9)=0,"",ROUND(AVERAGE(BH9:BK9),0)) | BH9: =IF(BL9="","",IF(BL9>=90,"HOT",IF(BL9>=75,"HIGH",IF(BL9>=50,"MEDIUM","LOW")))) | BL9: =IFERROR(BN9/12,"")
AE10: =IF(A10="","",IFERROR(MAXIFS(Activities!$D:$D,Activities!$B:$B,A10),"")) | AF10: =IF(A10="","",IFERROR(MINIFS(Follow_Ups!$G:$G,Follow_Ups!$B:$B,A10,Follow_Ups!$H:$H,"<>Completed",Follow_Ups!$G:$G,">="&TODAY()),"")) | AG10: =IF(A10="","",COUNTIF(Activities!$B:$B,A10)) | BG10: =IF(COUNTA(BH10:BK10)=0,"",ROUND(AVERAGE(BH10:BK10),0)) | BH10: =IF(BL10="","",IF(BL10>=90,"HOT",IF(BL10>=75,"HIGH",IF(BL10>=50,"MEDIUM","LOW")))) | BL10: =IFERROR(BN10/12,"")
AE11: =IF(A11="","",IFERROR(MAXIFS(Activities!$D:$D,Activities!$B:$B,A11),"")) | AF11: =IF(A11="","",IFERROR(MINIFS(Follow_Ups!$G:$G,Follow_Ups!$B:$B,A11,Follow_Ups!$H:$H,"<>Completed",Follow_Ups!$G:$G,">="&TODAY()),"")) | AG11: =IF(A11="","",COUNTIF(Activities!$B:$B,A11)) | BG11: =IF(COUNTA(BH11:BK11)=0,"",ROUND(AVERAGE(BH11:BK11),0)) | BH11: =IF(BL11="","",IF(BL11>=90,"HOT",IF(BL11>=75,"HIGH",IF(BL11>=50,"MEDIUM","LOW")))) | BL11: =IFERROR(BN11/12,"")
AE12: =IF(A12="","",IFERROR(MAXIFS(Activities!$D:$D,Activities!$B:$B,A12),"")) | AF12: =IF(A12="","",IFERROR(MINIFS(Follow_Ups!$G:$G,Follow_Ups!$B:$B,A12,Follow_Ups!$H:$H,"<>Completed",Follow_Ups!$G:$G,">="&TODAY()),"")) | AG12: =IF(A12="","",COUNTIF(Activities!$B:$B,A12)) | BG12: =IF(COUNTA(BH12:BK12)=0,"",ROUND(AVERAGE(BH12:BK12),0)) | BH12: =IF(BL12="","",IF(BL12>=90,"HOT",IF(BL12>=75,"HIGH",IF(BL12>=50,"MEDIUM","LOW")))) | BL12: =IFERROR(BN12/12,"")
AE13: =IF(A13="","",IFERROR(MAXIFS(Activities!$D:$D,Activities!$B:$B,A13),"")) | AF13: =IF(A13="","",IFERROR(MINIFS(Follow_Ups!$G:$G,Follow_Ups!$B:$B,A13,Follow_Ups!$H:$H,"<>Completed",Follow_Ups!$G:$G,">="&TODAY()),"")) | AG13: =IF(A13="","",COUNTIF(Activities!$B:$B,A13)) | BG13: =IF(COUNTA(BH13:BK13)=0,"",ROUND(AVERAGE(BH13:BK13),0)) | BH13: =IF(BL13="","",IF(BL13>=90,"HOT",IF(BL13>=75,"HIGH",IF(BL13>=50,"MEDIUM","LOW")))) | BL13: =IFERROR(BN13/12,"")
... AE501: =IF(A501="","",IFERROR(MAXIFS(Activities!$D:$D,Activities!$B:$B,A501),"")) | AF501: =IF(A501="","",IFERROR(MINIFS(Follow_Ups!$G:$G,Follow_Ups!$B:$B,A501,Follow_Ups!$H:$H,"<>Completed",Follow_Ups!$G:$G,">="&TODAY()),"")) | AG501: =IF(A501="","",COUNTIF(Activities!$B:$B,A501)) | BG501: =IF(COUNTA(BH501:BK501)=0,"",ROUND(AVERAGE(BH501:BK501),0)) | BH501: =IF(BL501="","",IF(BL501>=90,"HOT",IF(BL501>=75,"HIGH",IF(BL501>=50,"MEDIUM","LOW")))) | BL501: =IFERROR(BN501/12,"")

Sheet Contacts
A1: Contact ID | B1: Lead ID | C1: Business Name | D1: First Name | E1: Last Name | F1: Title / Role | G1: Decision Maker? | H1: Phone | I1: Email | J1: LinkedIn | K1: Instagram | L1: Preferred Contact Method | M1: Contact Status | N1: Notes

Sheet Activities
A1: Activity ID | B1: Lead ID | C1: Business Name | D1: Date | E1: Time | F1: Activity Type | G1: Direction | H1: Contact Method | I1: Contact Person | J1: Outcome | K1: Response / Summary | L1: Objection | M1: Follow-Up Required? | N1: Follow-Up Date | O1: Next Action | P1: Notes

Sheet Follow_Ups
A1: Follow-Up ID | B1: Lead ID | C1: Business Name | D1: Sequence | E1: Follow-Up Type | F1: Owner | G1: Due Date | H1: Status | I1: Priority | J1: Reason | K1: Completed Date | L1: Outcome | M1: Notes

Sheet Opportunities
A1: Opportunity ID | B1: Lead ID | C1: Business Name | D1: Opportunity Name | E1: Plan | F1: Pipeline Stage | G1: Probability | H1: Estimated Deal Value | I1: Estimated MRR | J1: Setup Fee | K1: Expected Close | L1: Proposal Date | M1: Close Date | N1: Won/Lost | O1: Lost Reason | P1: Primary Use Case | Q1: Notes
G2: =IF(F2="","",SWITCH(F2,"Qualified",0.1,"Discovery",0.2,"Demo Booked",0.35,"Demo Completed",0.5,"Proposal",0.65,"Negotiation",0.8,"Closed Won",1,0))
G3: =IF(F3="","",SWITCH(F3,"Qualified",0.1,"Discovery",0.2,"Demo Booked",0.35,"Demo Completed",0.5,"Proposal",0.65,"Negotiation",0.8,"Closed Won",1,0))
G4: =IF(F4="","",SWITCH(F4,"Qualified",0.1,"Discovery",0.2,"Demo Booked",0.35,"Demo Completed",0.5,"Proposal",0.65,"Negotiation",0.8,"Closed Won",1,0))
G5: =IF(F5="","",SWITCH(F5,"Qualified",0.1,"Discovery",0.2,"Demo Booked",0.35,"Demo Completed",0.5,"Proposal",0.65,"Negotiation",0.8,"Closed Won",1,0))
G6: =IF(F6="","",SWITCH(F6,"Qualified",0.1,"Discovery",0.2,"Demo Booked",0.35,"Demo Completed",0.5,"Proposal",0.65,"Negotiation",0.8,"Closed Won",1,0))
G7: =IF(F7="","",SWITCH(F7,"Qualified",0.1,"Discovery",0.2,"Demo Booked",0.35,"Demo Completed",0.5,"Proposal",0.65,"Negotiation",0.8,"Closed Won",1,0))
G8: =IF(F8="","",SWITCH(F8,"Qualified",0.1,"Discovery",0.2,"Demo Booked",0.35,"Demo Completed",0.5,"Proposal",0.65,"Negotiation",0.8,"Closed Won",1,0))
G9: =IF(F9="","",SWITCH(F9,"Qualified",0.1,"Discovery",0.2,"Demo Booked",0.35,"Demo Completed",0.5,"Proposal",0.65,"Negotiation",0.8,"Closed Won",1,0))
G10: =IF(F10="","",SWITCH(F10,"Qualified",0.1,"Discovery",0.2,"Demo Booked",0.35,"Demo Completed",0.5,"Proposal",0.65,"Negotiation",0.8,"Closed Won",1,0))
G11: =IF(F11="","",SWITCH(F11,"Qualified",0.1,"Discovery",0.2,"Demo Booked",0.35,"Demo Completed",0.5,"Proposal",0.65,"Negotiation",0.8,"Closed Won",1,0))
G12: =IF(F12="","",SWITCH(F12,"Qualified",0.1,"Discovery",0.2,"Demo Booked",0.35,"Demo Completed",0.5,"Proposal",0.65,"Negotiation",0.8,"Closed Won",1,0))
G13: =IF(F13="","",SWITCH(F13,"Qualified",0.1,"Discovery",0.2,"Demo Booked",0.35,"Demo Completed",0.5,"Proposal",0.65,"Negotiation",0.8,"Closed Won",1,0))
... G501: =IF(F501="","",SWITCH(F501,"Qualified",0.1,"Discovery",0.2,"Demo Booked",0.35,"Demo Completed",0.5,"Proposal",0.65,"Negotiation",0.8,"Closed Won",1,0))

Sheet Customers
A1: Customer ID | B1: Lead ID | C1: Business Name | D1: Primary Contact | E1: Plan | F1: Currency | G1: MRR | H1: Setup Fee | I1: Start Date | J1: Status | K1: Seats | L1: Locations | M1: Products | N1: Customers | O1: Current Features | P1: Expansion Opportunity | Q1: Renewal / Review Date | R1: Notes

Sheet Lead_Research
A1: Lead ID | B1: Business Name | C1: Has Website? | D1: Website Platform | E1: Website Quality | F1: Mobile Quality | G1: Custom Domain? | H1: HTTPS? | I1: Online Booking? | J1: Booking Method | K1: Online Payments? | L1: Ecommerce? | M1: Contact Form? | N1: Chat? | O1: Reviews Displayed? | P1: Gallery? | Q1: Blog? | R1: Customer Portal? | S1: Current Booking Software | T1: Current Payment Software | U1: Current CRM | V1: Current Accounting | W1: Current Invoicing | X1: Current Email Marketing | Y1: Current POS | Z1: Research Notes | AA1: Researcher | AB1: Research Date

Sheet Feature_Catalog
A1: Feature ID | B1: Module | C1: Feature | D1: Description | E1: Available? | F1: Minimum Tier | G1: Sales Value | H1: Best Fit Industries | I1: Primary Pain Point Solved | J1: Sales Talking Point
A2: F001 | B2: Storefront | C2: Branded Storefront | D2: Public merchant storefront with themes | E2: Yes | F2: Starter | G2: High | H2: All | I2: Outdated/no website | J2: Give customers a professional branded home base.
A3: F002 | B3: Commerce | C3: Products | D3: Physical and digital products, variants and inventory | E3: Yes | F3: Free | G3: High | H3: Retail, creators, wholesale | I3: Manual catalog | J3: Manage products and inventory in one place.
A4: F003 | B4: Scheduling | C4: Scheduling | D4: Availability, slots, guest booking, intake and policies | E4: Yes | F4: Free | G4: Very High | H4: Service businesses | I4: No booking/manual booking | J4: Let customers book without the back-and-forth.
A5: F004 | B5: Reviews | C5: Reviews | D5: Merchant-moderated customer reviews | E5: Yes | F5: Free | G5: Medium | H5: Service businesses | I5: No social proof | J5: Showcase customer feedback directly on your storefront.
A6: F005 | B6: CRM | C6: Messages | D6: Customer inquiries and messages | E6: Yes | F6: Free | G6: High | H6: All | I6: Scattered inquiries | J6: Keep customer conversations organized.
A7: F006 | B7: Marketing | C7: Emails | D7: Merchant email tools | E7: Yes | F7: Free | G7: High | H7: All | I7: Manual communication | J7: Centralize customer communication.
A8: F007 | B8: Marketing | C8: Newsletter | D8: Newsletter signup/content | E8: Yes | F8: Free | G8: Medium | H8: All | I8: No lead capture | J8: Turn visitors into an owned audience.
A9: F008 | B9: Content | C9: Blog | D9: Merchant blog | E9: Yes | F9: Free | G9: Medium | H9: All | I9: Weak SEO/content | J9: Publish useful content and build authority.
A10: F009 | B10: Website | C10: Themes | D10: Theme system/customization | E10: Yes | F10: Starter | G10: High | H10: All | I10: Weak branding | J10: Make the storefront look like your business.
A11: F010 | B11: Operations | C11: Admin | D11: Merchant admin and operational controls | E11: Yes | F11: Free | G11: Very High | H11: All | I11: Too many tools | J11: Run the business from one admin.
A12: F011 | B12: Operations | C12: Automations | D12: Active automations subject to tier limits | E12: Yes | F12: Starter | G12: Very High | H12: Growing service businesses | I12: Manual follow-up | J12: Automate repeatable work as you grow.
... A18: F017 | B18: Enterprise | C18: SSO | D18: SAML/OIDC SSO | E18: Yes | F18: Enterprise | G18: High | H18: Larger organizations | I18: Security/procurement | J18: Enterprise identity and procurement support.

Sheet Plan_Catalog
A1: Plan | B1: Monthly CAD | C1: Storage | D1: Team Seats | E1: Products | F1: Customer Profiles | G1: Sales Channels | H1: Locations | I1: Multi-location Inventory | J1: Active Automations | K1: Advanced Reporting | L1: Exports / Month | M1: Audit Retention | N1: Custom Themes | O1: Custom Domain | P1: Remove Branding | Q1: API RPM | R1: Support | S1: Priority Queue | T1: SSO | U1: Positioning
A2: Free | B2: 0 | C2: 5 MB | D2: 1 | E2: 25 | F2: 100 | G2: 1 | H2: 1 | I2: No | J2: 0 | K2: No | L2: 1 | M2: 30 days | N2: No | O2: No | P2: No | Q2: 60 | R2: Community | S2: No | T2: No | U2: Entry
A3: Starter | B3: 30 | C3: 1 GB | D3: 3 | E3: 500 | F3: 5000 | G3: 2 | H3: 1 | I3: No | J3: 5 | K3: No | L3: 4 | M3: 90 days | N3: Yes | O3: Yes | P3: No | Q3: 120 | R3: Email | S3: No | T3: No | U3: Small business
A4: Grow | B4: 46 | C4: 10 GB | D4: 10 | E4: 5000 | F4: 50000 | G4: 5 | H4: 3 | I4: Yes | J4: 25 | K4: Yes | L4: Unlimited | M4: 365 days | N4: Yes | O4: Yes | P4: Yes | Q4: 300 | R4: Email | S4: No | T4: No | U4: Growing business
A5: Pro | B5: 90 | C5: 100 GB | D5: Unlimited | E5: Unlimited | F5: Unlimited | G5: Unlimited | H5: 10 | I5: Yes | J5: Unlimited | K5: Yes | L5: Unlimited | M5: 730 days | N5: Yes | O5: Yes | P5: Yes | Q5: 600 | R5: Priority | S5: Yes | T5: No | U5: Advanced
A6: Enterprise | B6: Custom | C6: 1 TB | D6: Unlimited | E6: Unlimited | F6: Unlimited | G6: Unlimited | H6: Unlimited | I6: Yes | J6: Unlimited | K6: Yes | L6: Unlimited | M6: 2555 days | N6: Yes | O6: Yes | P6: Yes | Q6: Unlimited | R6: Dedicated | S6: Yes | T6: Yes | U6: Enterprise

Sheet Industry_Catalog
A1: Industry | B1: Sub-Industry | C1: Priority | D1: Peak Fit | E1: Typical Workflow | F1: Typical Pain Points | G1: Features To Emphasize | H1: Notes
A2: Home Services | B2: Landscaping | C2: High | D2: 95 | E2: Lead → Quote → Schedule → Service → Invoice | F2: Phone scheduling; manual follow-up; weak website | G2: Storefront; Scheduling; Messages; Emails; Automations | H2: Strong cold-call target
A3: Home Services | B3: Snow Removal | C3: High | D3: 93 | E3: Lead → Quote → Schedule → Service → Invoice | F3: Seasonal demand; scheduling; repeat customers | G3: Storefront; Scheduling; Messages; Automations | H3: Seasonality matters
A4: Transportation | B4: Towing | C4: High | D4: 90 | E4: Call → Dispatch → Service → Invoice | F4: Phone-heavy intake; customer records; invoicing | G4: Storefront; Messages; Admin; Scheduling | H4: Urgent service
A5: Transportation | B5: Trucking / Freight | C5: High | D5: 88 | E5: Lead → Quote → Dispatch → Invoice | F5: Multiple systems; customer records; B2B communication | G5: Messages; Admin; Analytics; API | H5: May need integrations
A6: Home Services | B6: Junk Removal | C6: High | D6: 92 | E6: Lead → Quote → Schedule → Service → Invoice | F6: Manual estimates; phone booking | G6: Storefront; Scheduling; Messages; Automations | H6: Strong fit
A7: Home Services | B7: Pressure Washing | C7: High | D7: 94 | E7: Lead → Quote → Schedule → Service → Invoice | F7: No booking; weak website; manual follow-up | G7: Storefront; Scheduling; Messages; Reviews | H7: Visual before/after opportunity
A8: Beauty | B8: Lash / Brow | C8: High | D8: 96 | E8: Lead → Book → Intake → Service → Review | F8: Instagram DMs; no website; manual booking | G8: Storefront; Scheduling; Reviews; Messages; Emails | H8: Excellent fit
A9: Creative | B9: Photography | C9: High | D9: 97 | E9: Inquiry → Consultation → Booking → Invoice → Delivery | F9: Scattered tools; deposits; portfolio | G9: Storefront; Scheduling; Products; Messages | H9: Excellent demo
A10: Events | B10: Wedding Vendor | C10: High | D10: 95 | E10: Inquiry → Consultation → Booking → Deposit → Delivery | F10: Manual follow-up; scattered systems | G10: Storefront; Scheduling; Messages; Emails; Admin | H10: High-value clients
A11: Wholesale | B11: B2B / Wholesale | C11: High | D11: 90 | E11: Inquiry → Approval → Quote/PO → Invoice | F11: Manual wholesale management | G11: Products; Customer Profiles; Admin; Analytics | H11: B2B sleeper market
A12: Professional Services | B12: Consultant / Coach | C12: High | D12: 94 | E12: Lead → Discovery → Booking → Invoice | F12: Calendars; forms; scattered client info | G12: Storefront; Scheduling; Messages; Emails; Admin | H12: Strong fit

Sheet Lead_Sources
A1: Source | B1: Source Type | C1: How Obtained | D1: Expected Quality | E1: Notes
A2: Google Maps | B2: Organic | C2: Manual / scraper | D2: Excellent | E2: Business, phone, website, reviews
A3: Google Search | B3: Organic | C3: Search / scraper | D3: Good | E3: Niche discovery
A4: Instagram | B4: Social | C4: Manual / scraper | D4: Excellent | E4: Strong for beauty/creative
A5: Facebook | B5: Social | C5: Manual / scraper | D5: Good | E5: Local services
A6: LinkedIn | B6: Social | C6: Manual / scraper | D6: Good | E6: B2B/professional
A7: Yelp | B7: Directory | C7: Directory | D7: Fair | E7: Enrichment
A8: Referral | B8: Referral | C8: Existing network | D8: Excellent | E8: Track referral source
A9: Cold List | B9: Outbound | C9: Scraper / list | D9: Unknown | E9: Validate before calling

Sheet Objections
A1: Objection | B1: Category | C1: Suggested Response | D1: Follow-Up Action | E1: Notes
A2: Too expensive | B2: Price | C2: Compare Peak's platform cost to multiple tools. | D2: Ask current monthly software spend. | E2: Avoid discounting immediately.
A3: Happy with current software | B3: Competition | C3: Ask what they like and where gaps remain. | D3: Research their stack. | E3: Position consolidation.
A4: Not right now | B4: Timing | C4: Ask when the problem becomes relevant. | D4: Create nurture follow-up. | E4: Capture timing.
A5: Need online payments | B5: Feature | C5: Qualify their payment workflow and explain processor fees are direct where supported. | D5: Track feature gap. | E5: Never overpromise.
A6: Need shipping | B6: Feature | C6: Qualify whether shipping is core. | D6: Nurture/disqualify if critical. | E6: Prioritize service businesses.

Sheet Sales_Templates
A1: Template ID | B1: Template Type | C1: Use Case | D1: Subject | E1: Template | F1: Notes
A2: T001 | B2: Call | C2: Cold call opener | E2: Hi [NAME], this is [NAME] with Peak. I was looking at [BUSINESS] and wanted to ask how you're currently handling [BOOKING / CUSTOMER MANAGEMENT / WEBSITE]. | F2: Personalize the pain point.
A3: T002 | B3: Voicemail | C3: No answer | E3: Hi [NAME], this is [NAME] with Peak. I had a quick question about how you're currently handling [PAIN POINT]. I'll try you again [DAY]. | F3: Keep under 20 seconds.
A4: T003 | B4: Email | C4: First touch | D4: Quick question about [BUSINESS] | E4: Hi [NAME], I came across [BUSINESS] and noticed [OBSERVATION]. Peak combines [FEATURES] into one platform. I wanted to see if [PAIN POINT] is something you're dealing with. | F4: Personalize observation.
A5: T004 | B5: Follow-Up | C5: After initial contact | D5: Following up — [BUSINESS] | E5: Hi [NAME], just following up on my note about [PAIN POINT]. If you're already happy with your setup, no problem — I was mainly curious whether [SPECIFIC ISSUE] is on your radar. | F5: Low pressure.

Sheet Scoring_Rules
A1: Score Component | B1: Weight | C1: How Scored | D1: Data Inputs | E1: Purpose
A2: Fit Score | B2: 0.25 | C2: 0-100 | D2: Industry, business model, size, workflow | E2: How well Peak fits
A3: Engagement Score | B3: 0.25 | C3: 0-100 | D3: Responses, activity, meetings, recency | E3: Interest
A4: Buying Potential | B4: 0.25 | C4: 0-100 | D4: Size, revenue, locations, pain severity | E4: Commercial potential
A5: Accessibility | B5: 0.25 | C5: 0-100 | D5: Decision-maker and valid contacts | E5: Reachability

Sheet Sales_Analytics
A1: Metric | B1: Value | C1: Definition
A2: Calls | B2: =COUNTIF(Activities!F:F,"Call") | C2: Logged calls
A3: Emails | B3: =COUNTIF(Activities!F:F,"Email") | C3: Logged emails
A4: Meetings | B4: =COUNTIF(Activities!F:F,"Meeting") | C4: Logged meetings
A5: Demos | B5: =COUNTIF(Activities!F:F,"Demo") | C5: Logged demos
A6: Proposals | B6: =COUNTIF(Activities!F:F,"Proposal") | C6: Logged proposal activities
A7: Wins | B7: =COUNTIF(Activities!J:J,"Won") | C7: Activities marked won

Sheet Activity_Analytics
A1: Metric | B1: Value | C1: Definition

Sheet Conversion_Analytics
A1: Stage | B1: Count | C1: Converted From Previous | D1: Conversion %
A2: Lead | B2: =COUNTA(Leads!A2:A501)
A3: Contacted | B3: =COUNTIF(Leads!AB2:AB501,"Contacted") | D3: =IFERROR(B3/B2,0)
A4: Engaged | B4: =COUNTIF(Leads!AB2:AB501,"Engaged") | D4: =IFERROR(B4/B3,0)
A5: Qualified | B5: =COUNTIF(Leads!AB2:AB501,"Qualified") | D5: =IFERROR(B5/B4,0)
A6: Demo | B6: =COUNTIF(Leads!BO2:BO501,"Demo Booked")+COUNTIF(Leads!BO2:BO501,"Demo Completed") | D6: =IFERROR(B6/B5,0)
A7: Proposal | B7: =COUNTIF(Leads!BO2:BO501,"Proposal") | D7: =IFERROR(B7/B6,0)
A8: Won | B8: =COUNTIF(Leads!AB2:AB501,"Customer") | D8: =IFERROR(B8/B7,0)

Sheet Revenue_Analytics
A1: Metric | B1: Value | C1: Definition

Sheet Locations
A1: Country | B1: Province/State | C1: City | D1: Postal/ZIP | E1: Territory | F1: Market | G1: Notes

Sheet Settings
A1: Setting | B1: Value | C1: Description

Sheet Dropdowns
A1: Lead Status | B1: Lead Source | C1: Contact Method | D1: Activity Type | E1: Activity Outcome | F1: Pipeline Stage | G1: Priority | H1: Decision Maker | I1: Yes No | J1: Website Quality | K1: Business Size | L1: Pain Point | M1: Lost Reason | N1: Website Platform | O1: Follow-Up Type | P1: Plan | Q1: Currency | R1: Contact Role | S1: Business Type | T1: Source Quality | U1: Customer Status | V1: Research Quality | W1: Follow-Up Status
A2: New | B2: Google Maps | C2: Phone | D2: Call | E2: No Answer | F2: Not Qualified | G2: Critical | H2: Yes | I2: Yes | J2: No Website | K2: Solo | L2: No Website | M2: Price | N2: Shopify | O2: Call | P2: Free | Q2: CAD | R2: Owner | S2: Sole Proprietor | T2: Excellent | U2: Prospect | V2: High | W2: Planned
A3: Researching | B3: Google Search | C3: Email | D3: Voicemail | E3: Voicemail Left | F3: Qualified | G3: High | H3: No | I3: No | J3: Poor | K3: Micro (2-9) | L3: Outdated Website | M3: No Need | N3: Wix | O3: Email | P3: Starter | Q3: USD | R3: Founder | S3: Partnership | T3: Good | U3: Customer | V3: Medium | W3: Due Today
A4: Ready to Contact | B4: Instagram | C4: SMS | D4: Email | E4: Connected | F4: Discovery | G4: Medium | H4: Unknown | I4: Unknown | J4: Basic | K4: Small (10-49) | L4: Poor Mobile Experience | M4: Timing | N4: Squarespace | O4: SMS | P4: Grow | R4: Co-Founder | S4: Corporation | T4: Fair | U4: Former Customer | V4: Low | W4: Overdue
A5: Contacted | B5: Facebook | C5: Instagram DM | D5: SMS | E5: Interested | F5: Demo Booked | G5: Low | J5: Good | K5: Medium (50-249) | L5: No Booking | M5: Chose Competitor | N5: WordPress | O5: DM | P5: Pro | R5: CEO | S5: Franchise | T5: Poor | U5: Expansion | V5: Unknown | W5: Completed
A6: Engaged | B6: LinkedIn | C6: Facebook Messenger | D6: DM | E6: Not Interested | F6: Demo Completed | G6: Nurture | J6: Excellent | K6: Large (250+) | L6: Phone-Only Booking | M6: Built In-House | N6: GoDaddy | O6: Meeting | P6: Enterprise | R6: General Manager | S6: Nonprofit | T6: Unknown | U6: Churned | W6: Skipped
A7: Qualified | B7: Yelp | C7: LinkedIn | D7: Meeting | E7: Callback Requested | F7: Proposal | J7: Unknown | K7: Unknown | L7: Manual Invoicing | M7: Unresponsive | N7: Webflow | O7: Demo | P7: Undetermined | R7: Manager | S7: Unknown
A8: Nurture | B8: Directory | C8: In Person | D8: Demo | E8: Qualified | F8: Negotiation | L8: No Customer Database | M8: Not a Fit | N8: Custom | O8: Proposal | R8: Marketing | S8: Other
A9: Opportunity | B9: Referral | C9: Video Call | D9: Proposal | E9: Demo Booked | F9: Closed Won | L9: Multiple Disconnected Systems | M9: Missing Feature | N9: Facebook | O9: Re-Engagement | R9: Sales
A10: Customer | B10: Website Research | C10: Other | D10: Follow-Up | E10: Demo Completed | F10: Closed Lost | L10: No Online Catalog | M10: Compliance | N10: Instagram | O10: Other | R10: Operations
A11: Disqualified | B11: Cold List | D11: Research | E11: Proposal Requested | F11: Nurture | L11: No Lead Capture | M11: Other | N11: None | R11: Admin
A12: Lost | B12: Other | D12: Other | E12: Proposal Sent | L12: No Follow-Up System | N12: Unknown | R12: Other
E13: Won | L13: No Automation | N13: Other
E14: Lost | L14: Poor Branding
E15: Wrong Number | L15: No Reviews Displayed
E16: Invalid Contact | L16: Other
E17: Other

Sheet Prospect_Discovery
A1: Prospect ID | B1: Business Name | C1: Industry | D1: City | E1: Source | F1: Search Query | G1: Website | H1: Phone | I1: Date Added | J1: Status | K1: Assigned | L1: Notes

Sheet Research_Engine
A1: Prospect ID | B1: Website Quality | C1: Reviews | D1: Years in Business | E1: Social Presence | F1: Tech Stack | G1: Decision Maker | H1: Pain Points | I1: Peak Fit | J1: Seasonality | K1: Best Callback | L1: Research Notes

Sheet Relationship_Timeline
A1: Date | B1: Prospect ID | C1: Business | D1: Contact | E1: Interaction | F1: Outcome | G1: Next Action | H1: Next Follow-up | I1: Timeline Notes
